bush/__init__.py
Bush_Encryption-0.3.dist-info/LICENSE
Bush_Encryption-0.3.dist-info/METADATA
Bush_Encryption-0.3.dist-info/WHEEL
Bush_Encryption-0.3.dist-info/bl.py
Bush_Encryption-0.3.dist-info/bl.pyi
Bush_Encryption-0.3.dist-info/top_level.txt
Bush_Encryption-0.3.dist-info/RECORD
