Metadata-Version: 2.1
Name: Bush-Encryption
Version: 0.3
Summary: Bush-Encryption A New Type Of Algorithm Using AES
Home-page: https://github.com/pmk456/Bush-Encryptor
Author: Patan Musthakheem
Author-email: patanmusthakheem786@gmail.com
License: Apache 2.0
Project-URL: Documentation, https://github.com/pmk456/Bush-Encryption
Project-URL: Source, https://github.com/pmk456/Bush-Encryption
Project-URL: Tracker, https://github.com/pmk456/Bush-Encryption/issues
Keywords: encryption,encryptors,aes
Platform: UNKNOWN
Classifier: License :: OSI Approved :: Apache Software License
Requires-Python: >=3.5
License-File: LICENSE
Requires-Dist: pycryptodome (>=3.9.6)
